aibe_server/__init__.py
aibe_server/config_manager.py
aibe_server/dependencies.py
aibe_server/main.py
aibe_server/server_manager.py
aibe_server/session_manager.py
aibe_server/story_assembler.py
aibe_server/extension/background.js
aibe_server/extension/content.entry.js
aibe_server/extension/content.js
aibe_server/extension/manifest.json
aibe_server/extension/package-lock.json
aibe_server/extension/package.json
aibe_server/extension/popup.html
aibe_server/extension/popup.js
aibe_server/middleware/__init__.py
aibe_server/middleware/session_middleware.py
aibe_server/models/__init__.py
aibe_server/models/commands.py
aibe_server/models/events.py
aibe_server/models/screen.py
aibe_server/models/sessions.py
aibe_server/persistence/__init__.py
aibe_server/persistence/base.py
aibe_server/persistence/mongodb_persistence.py
aibe_server/routers/actor.py
aibe_server/routers/legacy.py
aibe_server/routers/sessions.py
aibe_server/services/__init__.py
aibe_server/static/favicon.svg
aibe_server/streaming/__init__.py
aibe_server/streaming/server_streamer.py
aibe_server/tests/console-runner.js
aibe_server/tests/test-suites.json
aibe_server/tests/web-runner.html
aibe_server/tests/framework/DataDrivenTestRunner.js
aibe_server/tests/framework/GenericElementTest.js
aibe_server/tests/framework/TestingFramework.js
aibe_server/tests/pages/favicon.svg
aibe_server/tests/pages/test-controls.html
aibe_server/tests/pages/test-inputs.html
aibe_server/tests/pages/test-runner-web.html
aibe_server/utils/__init__.py
aibe_server/utils/logging.py
aibe_server/utils/process_management.py
aibe_server-1.0.0.dist-info/licenses/LICENSE
aibe_server-1.0.0.dist-info/METADATA
aibe_server-1.0.0.dist-info/WHEEL
aibe_server-1.0.0.dist-info/entry_points.txt
aibe_server-1.0.0.dist-info/top_level.txt
aibe_server-1.0.0.dist-info/RECORD
