Metadata-Version: 2.4
Name: aibe-server
Version: 1.0.0
Summary: AI Browser Extension Interface Server - enables AI systems to observe and control web browsers
Author-email: Paul Hanchett <paul@paulhanchett.com>
License-Expression: MIT
Project-URL: Homepage, https://paulhanchett.com/aibe
Project-URL: Documentation, https://paulhanchett.com/aibe/docs
Keywords: ai,browser,automation,generic-user-framework,web-interface
Classifier: Development Status :: 4 - Beta
Classifier: Intended Audience :: Developers
Classifier: Intended Audience :: Science/Research
Classifier: Topic :: Scientific/Engineering :: Artificial Intelligence
Classifier: Topic :: Software Development :: Libraries :: Python Modules
Classifier: Topic :: Internet :: WWW/HTTP :: Browsers
Classifier: Programming Language :: Python :: 3
Classifier: Programming Language :: Python :: 3.8
Classifier: Programming Language :: Python :: 3.9
Classifier: Programming Language :: Python :: 3.10
Classifier: Programming Language :: Python :: 3.11
Classifier: Programming Language :: Python :: 3.12
Requires-Python: >=3.8
License-File: LICENSE
Requires-Dist: fastapi>=0.104.1
Requires-Dist: uvicorn[standard]>=0.24.0
Requires-Dist: python-multipart>=0.0.6
Requires-Dist: aiofiles>=23.2.1
Requires-Dist: psutil>=5.9.6
Requires-Dist: requests>=2.25.1
Dynamic: license-file
